radler.cpython-313-x86_64-linux-gnu.so
radler.libs/libaec-91f0ca0f.so.0.0.8
radler.libs/libboost_date_time-abe26ce4.so.1.78.0
radler.libs/libbz2-a1e77c99.so.1.0.6
radler.libs/libcasa_casa-9e42215c.so.8
radler.libs/libcasa_fits-251fcf58.so.8
radler.libs/libcasa_measures-65a07e9b.so.8
radler.libs/libcasa_ms-60292d38.so.8
radler.libs/libcasa_scimath-e15f4aff.so.8
radler.libs/libcasa_scimath_f-2f3272ae.so.8
radler.libs/libcasa_tables-dd50aa6b.so.8
radler.libs/libcfitsio-b4c37dff.so.7.3.47
radler.libs/libfftw3-6b983104.so.3.5.5
radler.libs/libfftw3_threads-e9a1faec.so.3.5.5
radler.libs/libfftw3f-b4465a35.so.3.5.5
radler.libs/libfftw3f_threads-96b454f1.so.3.5.5
radler.libs/libgfortran-8f1e9814.so.5.0.0
radler.libs/libgsl-b64c76bc.so.23.1.0
radler.libs/libgslcblas-cd2c2030.so.0.0.0
radler.libs/libhdf5-b5e70f84.so.103.1.0
radler.libs/libhdf5_cpp-165bc8b8.so.103.1.0
radler.libs/libncurses-38c2e1a3.so.6.1
radler.libs/libopenblas-r0-11edc3fa.3.15.so
radler.libs/libquadmath-828275a7.so.0.0.0
radler.libs/libreadline-69c5979f.so.7.0
radler.libs/libsz-0deeef7d.so.2.0.1
radler.libs/libtinfo-3a2cb85b.so.6.1
radler-0.1.0.dist-info/METADATA
radler-0.1.0.dist-info/WHEEL
radler-0.1.0.dist-info/RECORD
radler-0.1.0.dist-info/licenses/LICENSE
radler-0.1.0.dist-info/licenses/LICENSE.LESSER
