Metadata-Version: 2.1
Name: radler
Version: 0.1.0
Summary: Radio Astronomical Deconvolution Library
Author-Email: Andre Offringa <offringa@astron.nl>, Maik Nijhuis <maik.nijhuis@triopsys.nl>, Jakob Maljaars <jakob.maljaars@stcorp.nl>, Tammo Jan Dijkema <dijkema@astron.nl>
Maintainer-Email: Marcel Loose <loose@astron.nl>, Tammo Jan Dijkema <dijkema@astron.nl>
Classifier: Development Status :: 4 - Beta
Classifier: License :: OSI Approved :: GNU Lesser General Public License v3 (LGPLv3)
Classifier: Topic :: Scientific/Engineering :: Astronomy
Project-URL: Documentation, https://radler.readthedocs.io/
Project-URL: Repository, https://git.astron.nl/RD/radler.git
Requires-Python: >=3.9
Requires-Dist: astropy
Requires-Dist: numpy
